cleanml/__init__.py
cleanml/cleanml.py
cleanml-0.2.0.dist-info/LICENSE
cleanml-0.2.0.dist-info/WHEEL
cleanml-0.2.0.dist-info/METADATA
cleanml-0.2.0.dist-info/RECORD
