Metadata-Version: 2.1
Name: cleanml
Version: 0.2.0
Summary: A package for cleaning and preparing data for ML models
License: MIT
Author: Thulasiram Gunipati
Requires-Python: >=3.9
Classifier: License :: OSI Approved :: MIT License
Classifier: Programming Language :: Python :: 3
Classifier: Programming Language :: Python :: 3.9
Classifier: Programming Language :: Python :: 3.10
Classifier: Programming Language :: Python :: 3.11
Requires-Dist: pandas (>=1.5.3)
